{
    "reporters": {
        "stats": {
            "confidence_intervals": {
                "levels": [
                    0.05,
                    0.95
                ],
                "method": "percentile",
                "replicates": 10000,
                "seed": 1
            },
            "type": "StatisticsReporter",
            "values": {
                "storage_data:dispx_center_inner:value_MEAN": {
                    "stat": "MEAN",
                    "type": "std::pair<double, std::vector<double>>"
                },
                "storage_data:dispx_center_inner:value_STDDEV": {
                    "stat": "STDDEV",
                    "type": "std::pair<double, std::vector<double>>"
                },
                "storage_data:dispx_center_outer:value_MEAN": {
                    "stat": "MEAN",
                    "type": "std::pair<double, std::vector<double>>"
                },
                "storage_data:dispx_center_outer:value_STDDEV": {
                    "stat": "STDDEV",
                    "type": "std::pair<double, std::vector<double>>"
                },
                "storage_data:dispx_end_inner:value_MEAN": {
                    "stat": "MEAN",
                    "type": "std::pair<double, std::vector<double>>"
                },
                "storage_data:dispx_end_inner:value_STDDEV": {
                    "stat": "STDDEV",
                    "type": "std::pair<double, std::vector<double>>"
                },
                "storage_data:dispx_end_outer:value_MEAN": {
                    "stat": "MEAN",
                    "type": "std::pair<double, std::vector<double>>"
                },
                "storage_data:dispx_end_outer:value_STDDEV": {
                    "stat": "STDDEV",
                    "type": "std::pair<double, std::vector<double>>"
                },
                "storage_data:dispz_inner:value_MEAN": {
                    "stat": "MEAN",
                    "type": "std::pair<double, std::vector<double>>"
                },
                "storage_data:dispz_inner:value_STDDEV": {
                    "stat": "STDDEV",
                    "type": "std::pair<double, std::vector<double>>"
                },
                "storage_data:dispz_outer:value_MEAN": {
                    "stat": "MEAN",
                    "type": "std::pair<double, std::vector<double>>"
                },
                "storage_data:dispz_outer:value_STDDEV": {
                    "stat": "STDDEV",
                    "type": "std::pair<double, std::vector<double>>"
                },
                "storage_data:temp_center_inner:value_MEAN": {
                    "stat": "MEAN",
                    "type": "std::pair<double, std::vector<double>>"
                },
                "storage_data:temp_center_inner:value_STDDEV": {
                    "stat": "STDDEV",
                    "type": "std::pair<double, std::vector<double>>"
                },
                "storage_data:temp_center_outer:value_MEAN": {
                    "stat": "MEAN",
                    "type": "std::pair<double, std::vector<double>>"
                },
                "storage_data:temp_center_outer:value_STDDEV": {
                    "stat": "STDDEV",
                    "type": "std::pair<double, std::vector<double>>"
                },
                "storage_data:temp_end_inner:value_MEAN": {
                    "stat": "MEAN",
                    "type": "std::pair<double, std::vector<double>>"
                },
                "storage_data:temp_end_inner:value_STDDEV": {
                    "stat": "STDDEV",
                    "type": "std::pair<double, std::vector<double>>"
                },
                "storage_data:temp_end_outer:value_MEAN": {
                    "stat": "MEAN",
                    "type": "std::pair<double, std::vector<double>>"
                },
                "storage_data:temp_end_outer:value_STDDEV": {
                    "stat": "STDDEV",
                    "type": "std::pair<double, std::vector<double>>"
                }
            }
        },
        "storage": {
            "type": "StochasticReporter",
            "values": {
                "data:converged": {
                    "row_begin": 0,
                    "row_end": 10,
                    "type": "std::vector<bool>"
                },
                "data:dispx_center_inner:value": {
                    "row_begin": 0,
                    "row_end": 10,
                    "type": "std::vector<double>"
                },
                "data:dispx_center_outer:value": {
                    "row_begin": 0,
                    "row_end": 10,
                    "type": "std::vector<double>"
                },
                "data:dispx_end_inner:value": {
                    "row_begin": 0,
                    "row_end": 10,
                    "type": "std::vector<double>"
                },
                "data:dispx_end_outer:value": {
                    "row_begin": 0,
                    "row_end": 10,
                    "type": "std::vector<double>"
                },
                "data:dispz_inner:value": {
                    "row_begin": 0,
                    "row_end": 10,
                    "type": "std::vector<double>"
                },
                "data:dispz_outer:value": {
                    "row_begin": 0,
                    "row_end": 10,
                    "type": "std::vector<double>"
                },
                "data:temp_center_inner:value": {
                    "row_begin": 0,
                    "row_end": 10,
                    "type": "std::vector<double>"
                },
                "data:temp_center_outer:value": {
                    "row_begin": 0,
                    "row_end": 10,
                    "type": "std::vector<double>"
                },
                "data:temp_end_inner:value": {
                    "row_begin": 0,
                    "row_end": 10,
                    "type": "std::vector<double>"
                },
                "data:temp_end_outer:value": {
                    "row_begin": 0,
                    "row_end": 10,
                    "type": "std::vector<double>"
                }
            }
        }
    },
    "time_steps": [
        {
            "stats": {
                "storage_data:dispx_center_inner:value_MEAN": [
                    0.0004043717679040656,
                    [
                        0.0003629096334329824,
                        0.00044673989434710905
                    ]
                ],
                "storage_data:dispx_center_inner:value_STDDEV": [
                    8.562603592126336e-05,
                    [
                        4.375052452809986e-05,
                        0.00011000312937357351
                    ]
                ],
                "storage_data:dispx_center_outer:value_MEAN": [
                    0.000499834474343884,
                    [
                        0.0004499212627105325,
                        0.0005510984420547323
                    ]
                ],
                "storage_data:dispx_center_outer:value_STDDEV": [
                    0.00010341976648193134,
                    [
                        5.153822106584897e-05,
                        0.0001340757491301816
                    ]
                ],
                "storage_data:dispx_end_inner:value_MEAN": [
                    0.00041246339321122396,
                    [
                        0.00035925540655631254,
                        0.0004672438847090685
                    ]
                ],
                "storage_data:dispx_end_inner:value_STDDEV": [
                    0.00011141847596845155,
                    [
                        7.107148686334474e-05,
                        0.00013249993651877294
                    ]
                ],
                "storage_data:dispx_end_outer:value_MEAN": [
                    0.0004700577454213585,
                    [
                        0.00041281056866434895,
                        0.0005289957571748794
                    ]
                ],
                "storage_data:dispx_end_outer:value_STDDEV": [
                    0.00011934433484294112,
                    [
                        7.53665532162217e-05,
                        0.00014308449995674384
                    ]
                ],
                "storage_data:dispz_inner:value_MEAN": [
                    0.0006084323494177848,
                    [
                        0.0005460736042680106,
                        0.0006729413499116678
                    ]
                ],
                "storage_data:dispz_inner:value_STDDEV": [
                    0.00012962351198686283,
                    [
                        7.278384561664884e-05,
                        0.0001644350650701214
                    ]
                ],
                "storage_data:dispz_outer:value_MEAN": [
                    0.0005043111537169073,
                    [
                        0.00044903212637305653,
                        0.0005608297493083688
                    ]
                ],
                "storage_data:dispz_outer:value_STDDEV": [
                    0.00011472460185008429,
                    [
                        6.61763536328713e-05,
                        0.00014423714323386004
                    ]
                ],
                "storage_data:temp_center_inner:value_MEAN": [
                    611.1375564276152,
                    [
                        600.9825855977663,
                        621.0283529032234
                    ]
                ],
                "storage_data:temp_center_inner:value_STDDEV": [
                    20.568574766097694,
                    [
                        14.072511652544023,
                        23.725142318734942
                    ]
                ],
                "storage_data:temp_center_outer:value_MEAN": [
                    587.9047948967435,
                    [
                        579.2797852205647,
                        596.3230537092386
                    ]
                ],
                "storage_data:temp_center_outer:value_STDDEV": [
                    17.548723222033,
                    [
                        11.875334541449337,
                        20.352520729256025
                    ]
                ],
                "storage_data:temp_end_inner:value_MEAN": [
                    506.97168653128904,
                    [
                        501.50905765962415,
                        512.6145254605099
                    ]
                ],
                "storage_data:temp_end_inner:value_STDDEV": [
                    11.449133440710021,
                    [
                        7.717806025279164,
                        13.40306280112824
                    ]
                ],
                "storage_data:temp_end_outer:value_MEAN": [
                    508.58934480784075,
                    [
                        502.87869194524137,
                        514.4500480367327
                    ]
                ],
                "storage_data:temp_end_outer:value_STDDEV": [
                    11.909750258969705,
                    [
                        8.030036243853257,
                        13.99055861654749
                    ]
                ]
            },
            "storage": {
                "data:converged": [
                    true,
                    true,
                    true,
                    true,
                    true,
                    true,
                    true,
                    true,
                    true,
                    true
                ],
                "data:dispx_center_inner:value": [
                    0.00038981809292440304,
                    0.0005557976925779025,
                    0.0004350332448897711,
                    0.000392081399230247,
                    0.0003254518522948608,
                    0.00038286899863544194,
                    0.00041863505314375995,
                    0.00024257411116796943,
                    0.0004039151432434001,
                    0.0004975420909328994
                ],
                "data:dispx_center_outer:value": [
                    0.0004748915272611948,
                    0.0006858709019064146,
                    0.0005499415286560498,
                    0.00048153682874098243,
                    0.0004135199630174104,
                    0.00048107387809846297,
                    0.000521263960229656,
                    0.0003028976664647329,
                    0.00048328271252421777,
                    0.0006040657765397197
                ],
                "data:dispx_end_inner:value": [
                    0.00033738607961145774,
                    0.0005781104607816505,
                    0.0005630463079498737,
                    0.0003682608476776031,
                    0.00041590993738599034,
                    0.00048439765988899205,
                    0.0004566283039531367,
                    0.00026548841630006796,
                    0.0002538287589767906,
                    0.000401577159586677
                ],
                "data:dispx_end_outer:value": [
                    0.0003930969012823575,
                    0.00065454706843135,
                    0.0006274571684346239,
                    0.0004252720468732502,
                    0.00046287736765382697,
                    0.0005395920551870019,
                    0.0005152809018254456,
                    0.00029976353679637806,
                    0.0003103363910266193,
                    0.0004723540167027316
                ],
                "data:dispz_inner:value": [
                    0.0005450433920194955,
                    0.0008393560005100691,
                    0.000738259271373054,
                    0.000569417193771181,
                    0.0005495435989748031,
                    0.0006386472601071033,
                    0.0006496069857845152,
                    0.0003780068671184486,
                    0.0005001585588865534,
                    0.0006762843656326241
                ],
                "data:dispz_outer:value": [
                    0.0005064062590015968,
                    0.0006817113166678684,
                    0.0005107210145390209,
                    0.0005045489413059262,
                    0.0003801220744121496,
                    0.0004482715499408034,
                    0.0005093497180743623,
                    0.0002961018231021565,
                    0.0005502881553741723,
                    0.0006555906847510166
                ],
                "data:temp_center_inner:value": [
                    610.17927549069,
                    626.815107637753,
                    586.3367075650242,
                    635.0794787988215,
                    590.1750339778115,
                    580.2882734287862,
                    607.9369996340075,
                    608.8995121922303,
                    636.3601904019406,
                    629.3049851490873
                ],
                "data:temp_center_outer:value": [
                    588.5235224173697,
                    598.9554769500587,
                    568.0802427555324,
                    608.8508330498402,
                    570.0716491779972,
                    561.6250849597784,
                    582.197560392131,
                    586.4419109358931,
                    611.2246867793485,
                    603.0769815494862
                ],
                "data:temp_end_inner:value": [
                    508.8638228634077,
                    511.6706161637647,
                    497.8885330024392,
                    525.1086170442126,
                    493.43107146438837,
                    491.96259430386357,
                    499.9539711342405,
                    503.6012257336334,
                    519.6476612124156,
                    517.5887523905242
                ],
                "data:temp_end_outer:value": [
                    510.0950938303771,
                    514.2663619850595,
                    498.78507421392476,
                    527.643844989675,
                    494.2796684552679,
                    493.0180624533907,
                    502.2372999032566,
                    504.73135246317395,
                    520.9527235052088,
                    519.883966279073
                ]
            },
            "time": 1.0,
            "time_step": 1
        }
    ]
}